MANIFEST.in
README
compare.py
setup.py
EnvComparison/__init__.py
EnvComparison/connection.py
EnvComparison/differ.py
EnvComparison/packages.py
EnvComparison/platform.py
EnvComparison/server.py
EnvComparison/site.py
EnvComparison/ssh_hosts.py
EnvComparison.egg-info/PKG-INFO
EnvComparison.egg-info/SOURCES.txt
EnvComparison.egg-info/dependency_links.txt
EnvComparison.egg-info/requires.txt
EnvComparison.egg-info/top_level.txt