Metadata-Version: 1.0
Name: EnvComparison
Version: 0.1.5
Summary: Linux Environment Comparison Tool
Home-page: https://github.com/adamar/EnvComparison
Author: Andrew Martin
Author-email: a.a.d.martin@gmail.com
License: UNKNOWN
Platform: UNKNOWN
